scan_pdf/__init__.py
scan_pdf/cli.py
scan_pdf/combine.py
scan_pdf/convert.py
scan_pdf/scan.py
scan_pdf/util.py
scan_pdf-0.4.8.dist-info/LICENSE
scan_pdf-0.4.8.dist-info/METADATA
scan_pdf-0.4.8.dist-info/WHEEL
scan_pdf-0.4.8.dist-info/entry_points.txt
scan_pdf-0.4.8.dist-info/RECORD
