Metadata-Version: 2.1
Name: scan-pdf
Version: 0.4.8
Summary: Tools for using scanners with document feeder
License: Apache-2.0
Author: Andreas Würl
Author-email: andi@tryb.de
Requires-Python: >=3.9,<4.0
Classifier: License :: OSI Approved :: Apache Software License
Classifier: Programming Language :: Python :: 3
Classifier: Programming Language :: Python :: 3.9
Classifier: Programming Language :: Python :: 3.10
Classifier: Programming Language :: Python :: 3.11
Classifier: Programming Language :: Python :: 3.12
Classifier: Programming Language :: Python :: 3.13
Requires-Dist: pypdf (>=5.1,<6.0)
